swdpp/__init__.py
swdpp/swdpp.py
swdpp-0.0.5.dist-info/LICENSE
swdpp-0.0.5.dist-info/METADATA
swdpp-0.0.5.dist-info/WHEEL
swdpp-0.0.5.dist-info/top_level.txt
swdpp-0.0.5.dist-info/RECORD
