Metadata-Version: 2.1
Name: swdpp
Version: 0.0.5
Summary: sliding window DPP
Home-page: UNKNOWN
Author: ks_one
Author-email: ks_one@163.com
License: UNKNOWN
Platform: UNKNOWN
Classifier: Programming Language :: Python :: 3
Classifier: License :: OSI Approved :: MIT License
Classifier: Operating System :: OS Independent
